{"repo": {"timestamp": 1631392253000, "version": 20000, "name": "Rboard F-Droid Repo", "icon": "fdroid-icon.png", "address": "https://raw.githubusercontent.com/GboardThemes/Repo/master", "description": "\nThis is a repository of apps to be used with F-Droid. Applications in this\nrepository are either official binaries built by the original application\ndevelopers, or are binaries built from source by the admin of f-droid.org\nusing the tools on https://gitlab.com/u/fdroid.\n"}, "requests": {"install": [], "uninstall": []}, "apps": [{"authorName": "DerTyp7214", "categories": ["Gboard", "Customization", "Keyboard", "Rboard", "Theming"], "suggestedVersionCode": "2147483647", "description": "Rboard Themes Manager App", "license": "MIT", "name": "Rboard Theme Manager V3", "sourceCode": "https://github.com/DerTyp7214/RboardThemeManagerV3.git", "summary": "Rboard Themes Manager App", "added": 1628951822000, "packageName": "de.dertyp7214.rboardthememanager", "lastUpdated": 1631392249000}], "packages": {"de.dertyp7214.rboardthememanager": [{"added": 1631392249000, "apkName": "manager-2021-09-11-2030.apk", "hash": "a52b3addf77ca67736fa4d956f0491e350f85e766e1eb5677df8b3b85d871961", "hashType": "sha256", "minSdkVersion": 31, "nativecode": ["arm64-v8a", "armeabi-v7a", "x86", "x86_64"], "packageName": "de.dertyp7214.rboardthememanager", "sig": "062ad597d06b456de1f8c672b7df0d61", "signer": "b01ff556b752eea00c491582a65259db98919c3fa6925149e50f32352a08faf4", "size": 20161406, "targetSdkVersion": 31, "uses-permission": [["android.permission.INTERNET", null], ["android.permission.REQUEST_DELETE_PACKAGES", null], ["android.permission.REQUEST_INSTALL_PACKAGES", null], ["android.permission.QUERY_ALL_PACKAGES", null], ["android.permission.ACCESS_NETWORK_STATE", null], ["android.permission.WAKE_LOCK", null], ["com.google.android.c2dm.permission.RECEIVE", null], ["com.google.android.finsky.permission.BIND_GET_INSTALL_REFERRER_SERVICE", null]], "versionCode": 328004, "versionName": "3.2.8"}, {"added": 1631199238000, "apkName": "manager-2021-09-09-1453.apk", "hash": "8cb9623a45f4653e02fe9eed144a55fabe9b52fb6b5be65d49dffe89caa51ef2", "hashType": "sha256", "minSdkVersion": 31, "nativecode": ["arm64-v8a", "armeabi-v7a", "x86", "x86_64"], "packageName": "de.dertyp7214.rboardthememanager", "sig": "062ad597d06b456de1f8c672b7df0d61", "signer": "b01ff556b752eea00c491582a65259db98919c3fa6925149e50f32352a08faf4", "size": 20157198, "targetSdkVersion": 31, "uses-permission": [["android.permission.INTERNET", null], ["android.permission.REQUEST_DELETE_PACKAGES", null], ["android.permission.REQUEST_INSTALL_PACKAGES", null], ["android.permission.QUERY_ALL_PACKAGES", null], ["android.permission.ACCESS_NETWORK_STATE", null], ["android.permission.WAKE_LOCK", null], ["com.google.android.c2dm.permission.RECEIVE", null], ["com.google.android.finsky.permission.BIND_GET_INSTALL_REFERRER_SERVICE", null]], "versionCode": 328003, "versionName": "3.2.8"}, {"added": 1631195047000, "apkName": "manager-2021-09-09-1344.apk", "hash": "5ece49db798d6a4f1998fcd206df1a8270e911386c868c105a7a058839e6c444", "hashType": "sha256", "minSdkVersion": 31, "nativecode": ["arm64-v8a", "armeabi-v7a", "x86", "x86_64"], "packageName": "de.dertyp7214.rboardthememanager", "sig": "062ad597d06b456de1f8c672b7df0d61", "signer": "b01ff556b752eea00c491582a65259db98919c3fa6925149e50f32352a08faf4", "size": 20157198, "targetSdkVersion": 31, "uses-permission": [["android.permission.INTERNET", null], ["android.permission.REQUEST_DELETE_PACKAGES", null], ["android.permission.REQUEST_INSTALL_PACKAGES", null], ["android.permission.QUERY_ALL_PACKAGES", null], ["android.permission.ACCESS_NETWORK_STATE", null], ["android.permission.WAKE_LOCK", null], ["com.google.android.c2dm.permission.RECEIVE", null], ["com.google.android.finsky.permission.BIND_GET_INSTALL_REFERRER_SERVICE", null]], "versionCode": 328002, "versionName": "3.2.8"}]}}