{
  "/etc/issue.net": "Ubuntu 20.04.4 LTS",
  "commandLine": [
    "/usr/bin/fdroid update"
  ],
  "fdroiddata": {
    "commitId": "74d01693808af0635fce70bf297ef9c6c0894d88",
    "isDirty": true,
    "modifiedFiles": [
      "archive/index-v1.jar",
      "archive/index-v1.json",
      "archive/index.jar",
      "archive/index.xml",
      "repo/index-v1.jar",
      "repo/index-v1.json",
      "repo/index.jar",
      "repo/index.xml",
      "repo/manager-2022-03-10-1950.apk",
      "tmp/apkcache.json"
    ],
    "untrackedFiles": [
      "archive/manager-2022-03-10-1950.apk",
      "repo/manager-2022-04-27-0932.apk"
    ]
  },
  "startTimestamp": 1651051945000,
  "subcommand": "update"
}